gradio_log/__init__.py
gradio_log/log.py
gradio_log/log.pyi
gradio_log/templates/component/index.js
gradio_log/templates/component/style.css
gradio_log-0.0.8.dist-info/METADATA
gradio_log-0.0.8.dist-info/WHEEL
gradio_log-0.0.8.dist-info/RECORD
