Metadata-Version: 2.3
Name: gradio_log
Version: 0.0.8
Summary: A Log component for Gradio which can easily show some log file in the interface.
Project-URL: Homepage, https://github.com/louis-she/gradio-log
Project-URL: Repository, https://github.com/louis-she/gradio-log
Author-email: Chenglu <chenglu.she@gmail.com>
License: Apache-2.0
Keywords: gradio-custom-component,gradio-template-SimpleTextbox,gradio_log,gradio_log_component,gradio_print_log,log
Classifier: Development Status :: 3 - Alpha
Classifier: License :: OSI Approved :: Apache Software License
Classifier: Operating System :: OS Independent
Classifier: Programming Language :: Python :: 3
Classifier: Programming Language :: Python :: 3 :: Only
Classifier: Programming Language :: Python :: 3.8
Classifier: Programming Language :: Python :: 3.9
Classifier: Programming Language :: Python :: 3.10
Classifier: Programming Language :: Python :: 3.11
Classifier: Topic :: Scientific/Engineering
Classifier: Topic :: Scientific/Engineering :: Artificial Intelligence
Classifier: Topic :: Scientific/Engineering :: Visualization
Requires-Python: >=3.8
Requires-Dist: gradio<6.0,>=4.0
Provides-Extra: dev
Requires-Dist: build; extra == 'dev'
Requires-Dist: twine; extra == 'dev'
